egrid/__init__.py
egrid/_types.py
egrid/builder.py
egrid/check.py
egrid/factors.py
egrid/model.py
egrid-0.0.7.dist-info/LICENSE
egrid-0.0.7.dist-info/METADATA
egrid-0.0.7.dist-info/WHEEL
egrid-0.0.7.dist-info/top_level.txt
egrid-0.0.7.dist-info/RECORD
