Metadata-Version: 2.1
Name: egrid
Version: 0.0.7
Summary: Model of an electric distribution network for calculation
Home-page: https://github.com/pyprg/egrid
Author: pyprg
Author-email: pyprg@outlook.com
Project-URL: Bug Tracker, https://github.com/pyprg/egrid/issues
Classifier: Programming Language :: Python :: 3
Classifier: License :: OSI Approved :: GNU General Public License v3 or later (GPLv3+)
Classifier: Operating System :: OS Independent
Requires-Python: >=3.6
License-File: LICENSE
Requires-Dist: graphparser >=0.8.4
Requires-Dist: networkx >=3.1
Requires-Dist: numpy >=1.24.3
Requires-Dist: pandas >=2.0.1
Requires-Dist: scipy >=1.10.1
